{
  "_buildCommand2" : {
    "command" : "build",
    "skipDependencies" : false,
    "style" : "buildAndRun"
  },
  "buildCommand" : "build",
  "configuredTargets" : [
    {
      "guid" : "ba0460cf17bbf96d0aa0e05fe9e912e7b0bb2a31f53c3dd270606965a24822ec"
    }
  ],
  "containerPath" : "/Users/mr.z/Documents/Learning Materials/LittlePink-GitCommandLine/LittlePink-GitCommandLine.xcodeproj",
  "continueBuildingAfterErrors" : false,
  "enableIndexBuildArena" : false,
  "hideShellScriptEnvironment" : false,
  "parameters" : {
    "action" : "build",
    "activeArchitecture" : "x86_64",
    "activeRunDestination" : {
      "disableOnlyActiveArch" : false,
      "platform" : "iphonesimulator",
      "sdk" : "iphonesimulator16.1",
      "sdkVariant" : "iphonesimulator",
      "supportedArchitectures" : [
        "x86_64"
      ],
      "targetArchitecture" : "x86_64"
    },
    "arenaInfo" : {
      "buildIntermediatesPath" : "/Users/mr.z/Documents/Learning Materials/LittlePink-GitCommandLine/Build/Intermediates.noindex",
      "buildProductsPath" : "/Users/mr.z/Documents/Learning Materials/LittlePink-GitCommandLine/Build/Products",
      "derivedDataPath" : "/Users/mr.z/Library/Developer/Xcode/DerivedData",
      "indexDataStoreFolderPath" : "/Users/mr.z/Library/Developer/Xcode/DerivedData/LittlePink-GitCommandLine-azzeudoycbgemmeilzvrdzxbqzhe/Index.noindex/DataStore",
      "indexEnableDataStore" : true,
      "indexPCHPath" : "/Users/mr.z/Library/Developer/Xcode/DerivedData/LittlePink-GitCommandLine-azzeudoycbgemmeilzvrdzxbqzhe/Index.noindex/PrecompiledHeaders",
      "pchPath" : "/Users/mr.z/Documents/Learning Materials/LittlePink-GitCommandLine/Build/Intermediates.noindex/PrecompiledHeaders"
    },
    "configurationName" : "Debug",
    "overrides" : {
      "synthesized" : {
        "table" : {
          "ASSETCATALOG_FILTER_FOR_DEVICE_MODEL" : "iPhone15,2",
          "ASSETCATALOG_FILTER_FOR_DEVICE_OS_VERSION" : "16.1",
          "ASSETCATALOG_FILTER_FOR_THINNING_DEVICE_CONFIGURATION" : "iPhone15,2",
          "BUILD_ACTIVE_RESOURCES_ONLY" : "YES",
          "ENABLE_PREVIEWS" : "NO",
          "TARGET_DEVICE_IDENTIFIER" : "685A8C5C-1252-4763-BA08-0869113E0542",
          "TARGET_DEVICE_MODEL" : "iPhone15,2",
          "TARGET_DEVICE_OS_VERSION" : "16.1",
          "TARGET_DEVICE_PLATFORM_NAME" : "iphonesimulator"
        }
      }
    }
  },
  "schemeCommand" : "launch",
  "schemeCommand2" : "launch",
  "showNonLoggedProgress" : true,
  "useDryRun" : false,
  "useImplicitDependencies" : true,
  "useLegacyBuildLocations" : false,
  "useParallelTargets" : true
}